dr_import/__init__.py
dr_import/analyze_gps.py
dr_import/analyze_trip.py
dr_import/clone_mrem_section.py
dr_import/clone_mrem_trip.py
dr_import/clone_mrem_trip_to_kept_catch.py
dr_import/clone_mrem_trips_to_noaa.py
dr_import/clone_trip.py
dr_import/create_concat_trip.py
dr_import/download_trip.py
dr_import/gps_utilities.py
dr_import/import_gps.py
dr_import/import_gps_legacy.py
dr_import/import_media.py
dr_import/import_poll_gps.py
dr_import/legacy_import.py
dr_import/local_gaps.py
dr_import/make_management_report.py
dr_import/make_trip.py
dr_import/nvr_import.py
dr_import/sample_gps.py
dr_import/trim_trip.py
dr_import/trip_summary.png
dr_import/update_media.py
dr_import-0.2.55.dist-info/METADATA
dr_import-0.2.55.dist-info/WHEEL
dr_import-0.2.55.dist-info/top_level.txt
dr_import-0.2.55.dist-info/RECORD
