Metadata-Version: 2.1
Name: dr-import
Version: 0.2.55
Summary: UNKNOWN
Home-page: https://www.cvisionai.com
Author: CVision AI
Author-email: info@cvisionai.com
Maintainer: CVision AI
Maintainer-email: info@cvisionai.com
License: UNKNOWN
Platform: UNKNOWN
Requires-Dist: boto3
Requires-Dist: numpy
Requires-Dist: openpyxl
Requires-Dist: pandas
Requires-Dist: pillow
Requires-Dist: plotly (==5.7.0)
Requires-Dist: pynmea2
Requires-Dist: python-dateutil
Requires-Dist: tator (>1.0.0)
Requires-Dist: tqdm
